msoffice2pdf/__init__.py
msoffice2pdf_UTF_8-1.0.0.2.dist-info/LICENSE
msoffice2pdf_UTF_8-1.0.0.2.dist-info/METADATA
msoffice2pdf_UTF_8-1.0.0.2.dist-info/WHEEL
msoffice2pdf_UTF_8-1.0.0.2.dist-info/top_level.txt
msoffice2pdf_UTF_8-1.0.0.2.dist-info/RECORD
