Metadata-Version: 2.1
Name: msoffice2pdf-UTF-8
Version: 1.0.0.2
Summary: This package aims to convert Office file types to PDF using Microsoft Office or LibreOffice.
Home-page: https://github.com/phosha/msoffice2pdf
Author: Robson Soares de Lima
Author-email: Phosha <kdrvpavel@gmail.com>
License: MIT
Keywords: msoffice,pdf,convert,libreoffice,.doc,.docx,.xls,.xlsx,.ppt,.pptx,.txt,.xml
Classifier: Topic :: Software Development
Classifier: Environment :: Win32 (MS Windows)
Classifier: Operating System :: Microsoft :: Windows
Classifier: Operating System :: Unix
Classifier: Topic :: Software Development :: Libraries
Classifier: Topic :: Software Development :: Libraries :: Python Modules
Requires-Python: >=3.6
License-File: LICENSE
